{
  "connections" : [
    {
      "id": "1",
      "source": "shape_67",
      "target": "shape_72",
      "targetGetsInfected": true,
      "nextTarget": [
        {
          "id": "2",
          "source": "shape_72",
          "target": "shape_61",
          "targetGetsInfected": true,
          "nextTarget": [
            {
              "id": "3",
              "source": "shape_91",
              "target": "shape_86",
              "targetGetsInfected": true,
              "nextTarget": [
                {
                  "id": "4",
                  "source": "shape_46",
                  "target": "shape_40",
                  "targetGetsInfected": true,
                  "nextTarget": [
                    {
                      "id": "5",
                      "source": "shape_40",
                      "target": "shape_31",
                      "targetGetsInfected": true,
                      "nextTarget": [
                      ]
                    },
                    {
                      "id": "5",
                      "source": "shape_40",
                      "target": "shape_45",
                      "targetGetsInfected": true,
                      "nextTarget": [
                        {
                          "id": "6",
                          "source": "shape_45",
                          "target": "shape_49",
                          "targetGetsInfected": true,
                          "endOfTheSequence": true,
                          "nextTarget": [
                            {
                              "id": "1",
                              "source": "shape_34",
                              "target": "shape_34",
                              "targetGetsInfected": true,
                              "nextTarget": [
                                {
                                  "id": "1",
                                  "source": "shape_16",
                                  "target": "shape_16",
                                  "targetGetsInfected": true,
                                  "nextTarget": [
                                  ]
                                }
                              ]
                            }
                          ]
                        }
                      ]
                    }
                  ]
                },
                {
                  "id": "4",
                  "source": "shape_71",
                  "target": "shape_71",
                  "targetGetsInfected": true,
                  "nextTarget": [
                  ]
                }
              ]
            }
          ]
        }
      ]
    }
  ]
}
