{
  "continueBtn" : "Lancer l'animation",
  "saveBtn" : "Sauvegarder",
  "saveEditBtn" : "Sauvegarder l'édition",
  "cancelBtn" : "Annuler",
  "resetAllBtn" : "Restaurer",
  "pageTitle" : "Créer votre groupe",
  "subtitle" : "Votre groupe",
  "generalInfo" : "Cliquer sur le personnage de votre choix afin de le personnaliser.",
  "finalInfo" : "Appuyer sur le bouton pour lancer l'animation",
  "skinColorTab" : "Peau",
  "hairColorTab" : "Cheveux",
  "glassesTab" : "Lunettes",
  "facialHairTab" : "Barbe/Mustache",
  "contextualInfoAvatar" : "Sélectionnez et personalisez votre propre avatar.",
  "nowSelect" : "Sélectionnez et personnalisez",
  "selectVulnerable": "personnes que vous considérez vulnerable.",
  "finallySelect" : "Finalement, selectionnez et personnalisez",
  "selectOthersPeople": "personnes de votre entourage.",
  "avatar": "votre avatar",
  "vulnerable": "une personne vulnérable",
  "otherPeople": "une personne de votre entourage",
  "language": "Changer la langue",
  "createAvatar": "Créez",
  "editAvatar": "Editez"
}
